pyrosetta_help/__init__.py
pyrosetta_help/colab_ops.py
pyrosetta_help/alphafold/__init__.py
pyrosetta_help/alphafold/constraints.py
pyrosetta_help/alphafold/multimodel.py
pyrosetta_help/alphafold/plot.py
pyrosetta_help/alphafold/retrieval.py
pyrosetta_help/alphafold/superimpose.py
pyrosetta_help/blueprint_maker/__init__.py
pyrosetta_help/blueprint_maker/_common.py
pyrosetta_help/blueprint_maker/_expected.py
pyrosetta_help/blueprint_maker/_init.py
pyrosetta_help/blueprint_maker/_pdb_info.py
pyrosetta_help/blueprint_maker/_remodel.py
pyrosetta_help/blueprint_maker/_subscripted.py
pyrosetta_help/chain_ops/__init__.py
pyrosetta_help/chain_ops/chain_ops.py
pyrosetta_help/chain_ops/transmogrifier.py
pyrosetta_help/common_ops/__init__.py
pyrosetta_help/common_ops/constraints.py
pyrosetta_help/common_ops/distances.py
pyrosetta_help/common_ops/downloads.py
pyrosetta_help/common_ops/faux_selectors.py
pyrosetta_help/common_ops/minimize.py
pyrosetta_help/common_ops/nglview.py
pyrosetta_help/common_ops/ss_changes.py
pyrosetta_help/common_ops/utils.py
pyrosetta_help/init_ops/__init__.py
pyrosetta_help/init_ops/log.py
pyrosetta_help/init_ops/make_options.py
pyrosetta_help/installer/__init__.py
pyrosetta_help/installer/_aux.py
pyrosetta_help/ligands/__init__.py
pyrosetta_help/ligands/hunter.py
pyrosetta_help/ligands/load.py
pyrosetta_help/ligands/nick.py
pyrosetta_help/per_atom/__init__.py
pyrosetta_help/residue_decription/__init__.py
pyrosetta_help/residue_decription/betaturn.py
pyrosetta_help/residue_decription/cis.py
pyrosetta_help/residue_decription/hbonds.py
pyrosetta_help/residue_decription/ss.py
pyrosetta_help/residue_decription/xlinks.py
pyrosetta_help/score_mutants/__init__.py
pyrosetta_help/score_mutants/mutation.py
pyrosetta_help/score_mutants/scores.py
pyrosetta_help/score_mutants/variant.py
pyrosetta_help/threading/__init__.py
pyrosetta_help/weights/__init__.py
pyrosetta_help/weights/terms.py
pyrosetta_help-0.5.4.dist-info/LICENSE
pyrosetta_help-0.5.4.dist-info/METADATA
pyrosetta_help-0.5.4.dist-info/WHEEL
pyrosetta_help-0.5.4.dist-info/entry_points.txt
pyrosetta_help-0.5.4.dist-info/top_level.txt
pyrosetta_help-0.5.4.dist-info/RECORD
