Metadata-Version: 2.1
Name: pyrosetta-help
Version: 0.5.4
Summary: A variety of functions to make working with Pyrosetta easier.
Home-page: https://github.com/matteoferla/pyrosetta_help
Author: Matteo Ferla
Author-email: matteo.ferla@gmail.com
License: MIT
Classifier: Development Status :: 4 - Beta
Classifier: Intended Audience :: Science/Research
Classifier: Topic :: Scientific/Engineering :: Bio-Informatics
Classifier: Topic :: Scientific/Engineering :: Chemistry
Classifier: License :: OSI Approved :: MIT License
Classifier: Programming Language :: Python :: 3.7
Classifier: Programming Language :: Python :: 3.8
Classifier: Programming Language :: Python :: 3.9
Requires-Python: >=3.7
License-File: LICENSE
Requires-Dist: rdkit-to-params
Requires-Dist: xerox
Requires-Dist: requests
Requires-Dist: pandas
Requires-Dist: biopython
